{
    "date": "2025-02-22",
    "day_shift": [
        {
            "파트": "CORE",
            "이름": "노광래",
            "근무": "주"
        },
        {
            "파트": "CORE",
            "이름": "양태훈",
            "근무": "주"
        },
        {
            "파트": "SVC",
            "이름": "김진택",
            "근무": "주"
        },
        {
            "파트": "SVC",
            "이름": "이대성",
            "근무": "주"
        }
    ],
    "night_shift": [
        {
            "파트": "CORE",
            "이름": "김석균",
            "근무": "야"
        },
        {
            "파트": "CORE",
            "이름": "김구선",
            "근무": "야"
        },
        {
            "파트": "SVC",
            "이름": "정보용",
            "근무": "야"
        },
        {
            "파트": "SVC",
            "이름": "한익진",
            "근무": "야"
        }
    ],
    "vacation_shift": []
}